{
  "generatedAt": "2026-04-19T00:51:22.349Z",
  "overall": "ok",
  "sources": [
    {
      "id": "imdb-top250",
      "itemCount": 248,
      "itemCountDelta": -1,
      "message": null,
      "status": "ok",
      "lastSuccessAt": "2026-04-19T00:50:52.584Z",
      "lastFailureAt": null,
      "consecutiveFailures": 0
    },
    {
      "id": "criterion",
      "itemCount": 1130,
      "itemCountDelta": 0,
      "message": null,
      "status": "ok",
      "lastSuccessAt": "2026-04-19T00:51:17.863Z",
      "lastFailureAt": "2026-04-18T23:36:48.793Z",
      "consecutiveFailures": 0
    },
    {
      "id": "afi-top100",
      "itemCount": 100,
      "itemCountDelta": 0,
      "message": null,
      "status": "ok",
      "lastSuccessAt": "2026-04-19T00:51:19.077Z",
      "lastFailureAt": null,
      "consecutiveFailures": 0
    },
    {
      "id": "bfi-ss-2022",
      "itemCount": 99,
      "itemCountDelta": 99,
      "message": null,
      "status": "ok",
      "lastSuccessAt": "2026-04-19T00:51:19.196Z",
      "lastFailureAt": null,
      "consecutiveFailures": 0
    }
  ]
}
